fixa/__init__.py
fixa/_version.py
fixa/better_enum.py
fixa/better_pathlib.py
fixa/binarysearch.py
fixa/build_dist.py
fixa/conventional_commits.py
fixa/dataclass_dataframe.py
fixa/deployment_pattern.py
fixa/emoji.py
fixa/env_var.py
fixa/git_cli.py
fixa/hashes.py
fixa/iterable.py
fixa/jsonutils.py
fixa/nest_logger.py
fixa/nested_logger.py
fixa/os_platform.py
fixa/pytest_cov_helper.py
fixa/rnd.py
fixa/runtime.py
fixa/runtime_v2.py
fixa/semantic_branch.py
fixa/timer.py
fixa/waiter.py
fixa/aws/__init__.py
fixa/aws/aws_athena_query.py
fixa/aws/aws_cloudwatch_logs_insights_query.py
fixa/aws/aws_dynamodb_export_to_s3.py
fixa/aws/aws_lambda_version_and_alias.py
fixa/aws/aws_s3_lock.py
fixa/aws/aws_s3_search.py
fixa/aws/aws_s3_static_website_hosting.py
fixa/aws/aws_s3_tracker.py
fixa/aws/aws_s3_uri.py
fixa/aws/aws_stepfunctions_version_and_alias.py
fixa/aws/aws_sts.py
fixa/aws/mock_test.py
fixa/docs/__init__.py
fixa/pylib/__init__.py
fixa/pylib/better_diskcache.py
fixa/pylib/better_fuzzywuzzy.py
fixa/tests/__init__.py
fixa-0.14.1.dist-info/AUTHORS.rst
fixa-0.14.1.dist-info/LICENSE.txt
fixa-0.14.1.dist-info/METADATA
fixa-0.14.1.dist-info/WHEEL
fixa-0.14.1.dist-info/top_level.txt
fixa-0.14.1.dist-info/RECORD
